resumify/__init__.py
resumify/resume.py
resumify/fonts/Ubuntu/Ubuntu-Bold.ttf
resumify/fonts/Ubuntu/Ubuntu-BoldItalic.ttf
resumify/fonts/Ubuntu/Ubuntu-Italic.ttf
resumify/fonts/Ubuntu/Ubuntu-Light.ttf
resumify/fonts/Ubuntu/Ubuntu-LightItalic.ttf
resumify/fonts/Ubuntu/Ubuntu-Medium.ttf
resumify/fonts/Ubuntu/Ubuntu-MediumItalic.ttf
resumify/fonts/Ubuntu/Ubuntu-Regular.ttf
resumify-1.1.7.dist-info/LICENSE
resumify-1.1.7.dist-info/METADATA
resumify-1.1.7.dist-info/WHEEL
resumify-1.1.7.dist-info/top_level.txt
resumify-1.1.7.dist-info/RECORD
